[
  {
    "alertId": 7,
    "alertType": "V",
    "alertTypeDescription": "Vulnerability",
    "alertCode": "VOP",
    "alertCodeDescription": "Rule 45 - Own Protection",
    "comment": null,
    "dateCreated": "2012-07-29",
    "expired": false,
    "active": true,
    "addedByFirstName": "RODERICK",
    "addedByLastName": "KSHLERIN",
    "expiredByFirstName": "LIZABETH",
    "expiredByLastName": "GRADY",
    "dateExpires": "2015-12-05"
  },
  {
    "alertId": 5,
    "alertType": "C",
    "alertTypeDescription": "Child Communication Measures",
    "alertCode": "CC1",
    "alertCodeDescription": "Child contact L1",
    "comment": null,
    "dateCreated": "2010-10-27",
    "expired": false,
    "active": true,
    "addedByFirstName": "ANGLEA",
    "addedByLastName": "VONRUEDEN",
    "expiredByFirstName": "STACEY",
    "expiredByLastName": "STEUBER",
    "dateExpires": "2018-07-18"
  },
  {
    "alertId": 6,
    "alertType": "C",
    "alertTypeDescription": "Child Communication Measures",
    "alertCode": "CPRC",
    "alertCodeDescription": "Potential PPRC",
    "comment": null,
    "dateCreated": "2012-02-02",
    "expired": false,
    "active": true,
    "addedByFirstName": "OTHA",
    "addedByLastName": "RAYNOR",
    "expiredByFirstName": "VERLINE",
    "expiredByLastName": "O'CONNER",
    "dateExpires": "2017-07-16"
  },
  {
    "alertId": 1,
    "alertType": "S",
    "alertTypeDescription": "Sexual Offence",
    "alertCode": "SC",
    "alertCodeDescription": "Risk to Children",
    "comment": null,
    "dateCreated": "2012-01-14",
    "expired": false,
    "active": true,
    "addedByFirstName": "HELEN",
    "addedByLastName": "WEISSNAT",
    "expiredByFirstName": "ROSENDA",
    "expiredByLastName": "GOTTLIEB",
    "dateExpires": "2015-08-29"
  },
  {
    "alertId": 2,
    "alertType": "S",
    "alertTypeDescription": "Sexual Offence",
    "alertCode": "SONR",
    "alertCodeDescription": "Sex offender not required to register",
    "comment": null,
    "dateCreated": "2010-10-03",
    "expired": false,
    "active": true,
    "addedByFirstName": "EDWARDO",
    "addedByLastName": "ROHAN",
    "expiredByFirstName": "LOWELL",
    "expiredByLastName": "WALKER",
    "dateExpires": "2015-12-06"
  },
  {
    "alertId": 3,
    "alertType": "P",
    "alertTypeDescription": "MAPPP Case",
    "alertCode": "PC1",
    "alertCodeDescription": "MAPPA Cat 1",
    "comment": null,
    "dateCreated": "2010-10-08",
    "expired": false,
    "active": true,
    "addedByFirstName": "NARCISA",
    "addedByLastName": "RICE",
    "expiredByFirstName": "LENARD",
    "expiredByLastName": "DONNELLY",
    "dateExpires": "2017-03-12"
  },
  {
    "alertId": 4,
    "alertType": "H",
    "alertTypeDescription": "Self Harm",
    "alertCode": "HA",
    "alertCodeDescription": "ACCT Open (HMPS)",
    "dateCreated": "2011-10-12",
    "dateExpires": "2017-06-03",
    "expired": true,
    "active": false,
    "addedByFirstName": "COREY",
    "addedByLastName": "BAILEY",
    "expiredByFirstName": "RUBY",
    "expiredByLastName": "DONNELLY",
    "comment": null
  }
]