[
  {
    "alertId": 11,
    "alertType": "X",
    "alertTypeDescription": "Security",
    "alertCode": "XNR",
    "alertCodeDescription": "Not For Release",
    "comment": null,
    "dateCreated": "2009-08-29",
    "expired": false,
    "active": true,
    "addedByFirstName": "JOSEF",
    "addedByLastName": "BLOCK",
    "expiredByFirstName": "STEVIE",
    "expiredByLastName": "GUTKOWSKI",
    "dateExpires": "2018-02-20"
  },
  {
    "alertId": 10,
    "alertType": "P",
    "alertTypeDescription": "MAPPP Case",
    "alertCode": "PVN",
    "alertCodeDescription": "ViSOR Nominal",
    "comment": null,
    "dateCreated": "2010-08-28",
    "expired": false,
    "active": true,
    "addedByFirstName": "CORI",
    "addedByLastName": "THOMPSON",
    "expiredByFirstName": "CAMERON",
    "expiredByLastName": "HAMMES",
    "dateExpires": "2016-10-16"
  },
  {
    "alertId": 6,
    "alertType": "R",
    "alertTypeDescription": "Risk",
    "alertCode": "RCC",
    "alertCodeDescription": "Risk to Children - Community",
    "comment": null,
    "dateCreated": "2010-05-28",
    "expired": false,
    "active": true,
    "addedByFirstName": "GIL",
    "addedByLastName": "CHAMPLIN",
    "expiredByFirstName": "TAMISHA",
    "expiredByLastName": "COLLINS",
    "dateExpires": "2018-08-13"
  },
  {
    "alertId": 5,
    "alertType": "C",
    "alertTypeDescription": "Child Communication Measures",
    "alertCode": "CPRC",
    "alertCodeDescription": "Potential PPRC",
    "comment": null,
    "dateCreated": "2010-03-08",
    "expired": false,
    "active": true,
    "addedByFirstName": "JARED",
    "addedByLastName": "REINGER",
    "expiredByFirstName": "HENRIETTA",
    "expiredByLastName": "HALEY",
    "dateExpires": "2015-02-17"
  },
  {
    "alertId": 4,
    "alertType": "C",
    "alertTypeDescription": "Child Communication Measures",
    "alertCode": "CC1",
    "alertCodeDescription": "Child contact L1",
    "comment": null,
    "dateCreated": "2010-06-11",
    "expired": false,
    "active": true,
    "addedByFirstName": "RENA",
    "addedByLastName": "HINTZ",
    "expiredByFirstName": "GINNY",
    "expiredByLastName": "RUNTE",
    "dateExpires": "2014-08-29"
  },
  {
    "alertId": 3,
    "alertType": "V",
    "alertTypeDescription": "Vulnerability",
    "alertCode": "VOP",
    "alertCodeDescription": "Rule 45 - Own Protection",
    "dateCreated": "2010-08-16",
    "expired": false,
    "active": true,
    "addedByFirstName": "JED",
    "addedByLastName": "LEFFLER",
    "expiredByFirstName": "TARI",
    "expiredByLastName": "HILPERT",
    "dateExpires": "2018-02-09",
    "comment": null
  },
  {
    "alertId": 1,
    "alertType": "S",
    "alertTypeDescription": "Sexual Offence",
    "alertCode": "SOR",
    "alertCodeDescription": "Registered sex offender",
    "comment": null,
    "dateCreated": "2012-08-09",
    "expired": false,
    "active": true,
    "addedByFirstName": "LAKEISHA",
    "addedByLastName": "SCHULTZ",
    "expiredByFirstName": "LOUELLA",
    "expiredByLastName": "DECKOW",
    "dateExpires": "2015-04-30"
  },
  {
    "alertId": 9,
    "alertType": "X",
    "alertTypeDescription": "Security",
    "alertCode": "XNR",
    "alertCodeDescription": "Not For Release",
    "comment": null,
    "dateCreated": "2011-07-30",
    "dateExpires": "2015-07-06",
    "expired": true,
    "active": false,
    "addedByFirstName": "TOBIAS",
    "addedByLastName": "ABERNATHY",
    "expiredByFirstName": "LANNY",
    "expiredByLastName": "HELLER"
  },
  {
    "alertId": 2,
    "alertType": "S",
    "alertTypeDescription": "Sexual Offence",
    "alertCode": "SSHO",
    "alertCodeDescription": "RSHO or SRO",
    "comment": null,
    "dateCreated": "2013-06-05",
    "dateExpires": "2016-11-04",
    "expired": true,
    "active": false,
    "addedByFirstName": "SUZANNA",
    "addedByLastName": "GRADY",
    "expiredByFirstName": "RANDALL",
    "expiredByLastName": "REILLY"
  },
  {
    "alertId": 8,
    "alertType": "H",
    "alertTypeDescription": "Self Harm",
    "alertCode": "HA1",
    "alertCodeDescription": "ACCT Post Closure (HMPS)",
    "comment": null,
    "dateCreated": "2013-08-09",
    "dateExpires": "2015-04-01",
    "expired": true,
    "active": false,
    "addedByFirstName": "WILBUR",
    "addedByLastName": "RAYNOR",
    "expiredByFirstName": "TAJUANA",
    "expiredByLastName": "HILLL"
  }
]