[
  {
    "alertId": 13,
    "alertType": "X",
    "alertTypeDescription": "Security",
    "alertCode": "XPOI",
    "alertCodeDescription": "Prisoner of Interest",
    "comment": null,
    "dateCreated": "2011-07-31",
    "expired": false,
    "active": true,
    "addedByFirstName": "SHELA",
    "addedByLastName": "STANTON",
    "expiredByFirstName": "MARCELLE",
    "expiredByLastName": "MURPHY",
    "dateExpires": "2014-11-19"
  },
  {
    "alertId": 12,
    "alertType": "R",
    "alertTypeDescription": "Risk",
    "alertCode": "RLO",
    "alertCodeDescription": "Low - Workplace Risk Assessment",
    "dateCreated": "2009-11-18",
    "expired": false,
    "active": true,
    "addedByFirstName": "YONG",
    "addedByLastName": "PROHASKA",
    "expiredByFirstName": "PAM",
    "expiredByLastName": "GREENHOLT",
    "dateExpires": "2016-06-06",
    "comment": null
  },
  {
    "alertId": 8,
    "alertType": "P",
    "alertTypeDescription": "MAPPP Case",
    "alertCode": "P0",
    "alertCodeDescription": "MAPPA Nominal",
    "dateCreated": "2013-06-16",
    "dateExpires": "2018-04-07",
    "expired": true,
    "active": false,
    "addedByFirstName": "KENDALL",
    "addedByLastName": "TROMP",
    "expiredByFirstName": "MABLE",
    "expiredByLastName": "HANSEN",
    "comment": null
  },
  {
    "alertId": 7,
    "alertType": "X",
    "alertTypeDescription": "Security",
    "alertCode": "XOCGN",
    "alertCodeDescription": "Organised Crime Group Nominal",
    "comment": null,
    "dateCreated": "2011-10-17",
    "dateExpires": "2017-09-22",
    "expired": true,
    "active": false,
    "addedByFirstName": "BLANCHE",
    "addedByLastName": "GRIMES",
    "expiredByFirstName": "CARMINE",
    "expiredByLastName": "CARTWRIGHT"
  },
  {
    "alertId": 11,
    "alertType": "T",
    "alertTypeDescription": "Hold Against Transfer",
    "alertCode": "TAP",
    "alertCodeDescription": "Accredited Programme hold",
    "comment": null,
    "dateCreated": "2010-08-11",
    "dateExpires": "2016-10-22",
    "expired": true,
    "active": false,
    "addedByFirstName": "GEORGANN",
    "addedByLastName": "STEUBER",
    "expiredByFirstName": "SHOSHANA",
    "expiredByLastName": "DARE"
  },
  {
    "alertId": 10,
    "alertType": "T",
    "alertTypeDescription": "Hold Against Transfer",
    "alertCode": "TAP",
    "alertCodeDescription": "Accredited Programme hold",
    "comment": null,
    "dateCreated": "2012-05-15",
    "dateExpires": "2015-11-22",
    "expired": true,
    "active": false,
    "addedByFirstName": "RICHIE",
    "addedByLastName": "VOLKMAN",
    "expiredByFirstName": "GARRETT",
    "expiredByLastName": "SCHUMM"
  },
  {
    "alertId": 9,
    "alertType": "T",
    "alertTypeDescription": "Hold Against Transfer",
    "alertCode": "TAP",
    "alertCodeDescription": "Accredited Programme hold",
    "comment": null,
    "dateCreated": "2012-04-15",
    "dateExpires": "2018-03-25",
    "expired": true,
    "active": false,
    "addedByFirstName": "LEMUEL",
    "addedByLastName": "HIRTHE",
    "expiredByFirstName": "LOU",
    "expiredByLastName": "SIPES"
  },
  {
    "alertId": 6,
    "alertType": "T",
    "alertTypeDescription": "Hold Against Transfer",
    "alertCode": "TM",
    "alertCodeDescription": "Medical Hold",
    "comment": null,
    "dateCreated": "2011-06-21",
    "dateExpires": "2014-10-02",
    "expired": true,
    "active": false,
    "addedByFirstName": "CHARA",
    "addedByLastName": "DAUGHERTY",
    "expiredByFirstName": "CARY",
    "expiredByLastName": "THOMPSON"
  },
  {
    "alertId": 4,
    "alertType": "X",
    "alertTypeDescription": "Security",
    "alertCode": "XNR",
    "alertCodeDescription": "Not For Release",
    "comment": null,
    "dateCreated": "2011-05-24",
    "dateExpires": "2016-04-21",
    "expired": true,
    "active": false,
    "addedByFirstName": "JARED",
    "addedByLastName": "BEAHAN",
    "expiredByFirstName": "FLO",
    "expiredByLastName": "GERHOLD"
  },
  {
    "alertId": 2,
    "alertType": "M",
    "alertTypeDescription": "Medical",
    "alertCode": "MFL",
    "alertCodeDescription": "False Limbs",
    "comment": null,
    "dateCreated": "2009-10-01",
    "dateExpires": "2018-04-15",
    "expired": true,
    "active": false,
    "addedByFirstName": "ARMANDO",
    "addedByLastName": "BINS",
    "expiredByFirstName": "EDMUND",
    "expiredByLastName": "WILDERMAN"
  }
]