[
  {
    "offenderNo": "T2564YT",
    "firstName": "Fermin",
    "middleNames": "Kieth",
    "lastName": "Tremblay",
    "dateOfBirth": "1978-12-19",
    "gender": "Female",
    "sexCode": "F",
    "nationalities": "Japanese",
    "currentlyInPrison": "N",
    "latestBookingId": 1234567,
    "latestLocationId": "ESI",
    "latestLocation": "EAST SUTTON PARK (HMP & YOI)",
    "internalLocation": "ABC-D-1-23",
    "pncNumber": "16/185372J",
    "croNumber": "56782/62X",
    "ethnicity": "Black/Black British: Any other Backgr'nd",
    "birthCountry": "Australia",
    "religion": "Muslim",
    "convictedStatus": "Convicted",
    "imprisonmentStatus": "TRL",
    "receptionDate": null,
    "maritalStatus": "Single-not married/in civil partnership"
  }
]