[
  {
    "offenderNo": "T6572PX",
    "firstName": "Gil",
    "middleNames": "Kyung",
    "lastName": "Zieme",
    "dateOfBirth": "1966-01-14",
    "gender": "Male",
    "sexCode": "M",
    "nationalities": "American",
    "currentlyInPrison": "N",
    "latestBookingId": 1234567,
    "latestLocationId": "GMI",
    "latestLocation": "GUYS MARSH (HMP)",
    "internalLocation": "ABC-D-1-23",
    "pncNumber": "93/238594E",
    "croNumber": "92756/16C",
    "ethnicity": "White: Any other background",
    "birthCountry": "Greece",
    "religion": "Atheist",
    "convictedStatus": "Remand",
    "imprisonmentStatus": "LR_ORA",
    "receptionDate": null,
    "maritalStatus": "Single-not married/in civil partnership"
  }
]
